nestipy_mailer/__init__.py
nestipy_mailer/mailer_builder.py
nestipy_mailer/mailer_module.py
nestipy_mailer/mailer_service.py
nestipy_mailer-0.1.2.dist-info/LICENSE
nestipy_mailer-0.1.2.dist-info/METADATA
nestipy_mailer-0.1.2.dist-info/WHEEL
nestipy_mailer-0.1.2.dist-info/RECORD
