Metadata-Version: 2.1
Name: nestipy-mailer
Version: 0.1.2
Summary: Nestipy is a Python framework built on top of BlackSheep that follows the modular architecture of NestJS
Author: tsiresymila
Author-email: tsiresymila@gmail.com
Requires-Python: >=3.11,<4.0
Classifier: Programming Language :: Python :: 3
Classifier: Programming Language :: Python :: 3.11
Classifier: Programming Language :: Python :: 3.12
Requires-Dist: aiosmtplib (>=3.0.1,<4.0.0)
